{"H3400":{"strong":"H3400","word":"יְרִיאֵל","translit":"ye.ri.el","brief_def":"Jeriel","full_def":""},"H3401":{"strong":"H3401","word":"יָרִיב","translit":"ya.riv","brief_def":"opponent","full_def":""},"H3402":{"strong":"H3402","word":"יָרִיב","translit":"ya.riv","brief_def":"Jarib","full_def":""},"H3403":{"strong":"H3403","word":"יְרִיבַי","translit":"ye.ri.vay","brief_def":"Jeribai","full_def":""},"H3404":{"strong":"H3404","word":"יְרִיָּהוּ","translit":"ye.riy.yah","brief_def":"Jerijah","full_def":""},"H3405":{"strong":"H3405","word":"יְרִיחוֹ","translit":"ye.ri.cho","brief_def":"(Plain of) Jericho","full_def":""},"H3406":{"strong":"H3406","word":"יְרֵמוֹת","translit":"ye.ri.mot","brief_def":"Jeremoth","full_def":""},"H3407":{"strong":"H3407","word":"יְרִיעָה","translit":"ye.ri.ah","brief_def":"curtain","full_def":""},"H3408":{"strong":"H3408","word":"יְרִיעוֹת","translit":"ye.ri.ot","brief_def":"Jerioth","full_def":""},"H3409":{"strong":"H3409","word":"יָרֵךְ","translit":"ya.rekh","brief_def":"thigh","full_def":""},"H3410":{"strong":"H3410","word":"יַרְכָא","translit":"yar.kah","brief_def":"thigh","full_def":""},"H3411":{"strong":"H3411","word":"יַרְכָה","translit":"ye.re.khah","brief_def":"flank","full_def":""},"H3412":{"strong":"H3412","word":"יַרְמוּת","translit":"yar.mut","brief_def":"Jarmuth","full_def":""},"H3413":{"strong":"H3413","word":"יְרֵמַי","translit":"ye.re.may","brief_def":"Jeremai","full_def":""},"H3414":{"strong":"H3414","word":"יִרְמְיָ֫הוּ","translit":"yir.me.yah","brief_def":"Jeremiah","full_def":""},"H3415":{"strong":"H3415","word":"יָרַע","translit":"ya.ra","brief_def":"be ill","full_def":""},"H3416":{"strong":"H3416","word":"יִרְפְּאֵל","translit":"yir.pe.el","brief_def":"Irpeel","full_def":""},"H3417":{"strong":"H3417","word":"יָרַק","translit":"ya.raq","brief_def":"to spit","full_def":""},"H3418":{"strong":"H3418","word":"יֶ֫רֶק","translit":"ye.req","brief_def":"green","full_def":""},"H3419":{"strong":"H3419","word":"יָרָק","translit":"ya.raq","brief_def":"herb","full_def":""},"H3420":{"strong":"H3420","word":"יֵרָקוֹן","translit":"ye.ra.qon","brief_def":"mildew","full_def":""},"H3421":{"strong":"H3421","word":"יׇרְקְעָ֑ם","translit":"yor.qe.am","brief_def":"Jorkeam","full_def":""},"H3422":{"strong":"H3422","word":"יְרַקְרַק","translit":"ye.raq.raq","brief_def":"greenish","full_def":""},"H3423":{"strong":"H3423","word":"יָרַשׁ","translit":"ya.rash","brief_def":"to possess: poor","full_def":""},"H3424":{"strong":"H3424","word":"יְרֵשָׁה","translit":"ye.re.shah","brief_def":"possession","full_def":""},"H3425":{"strong":"H3425","word":"יְרֻשָּׁה","translit":"ye.rush.shah","brief_def":"possession","full_def":""},"H3426":{"strong":"H3426","word":"יֵשׁ","translit":"yesh","brief_def":"there","full_def":""},"H3427":{"strong":"H3427","word":"יָשַׁב","translit":"ya.shav","brief_def":"to dwell","full_def":""},"H3428":{"strong":"H3428","word":"יֶֽשֶׁבְאָב","translit":"ye.shev.av","brief_def":"Jeshebeab","full_def":""},"H3429":{"strong":"H3429","word":"יֹשֵׁב בַּשֶּׁ֫בֶת","translit":"yo.shev bash.she.vet","brief_def":"Josheb-basshebeth","full_def":""},"H3430":{"strong":"H3430","word":"יִשְׁבּוֹ בְּנֹב","translit":"yish.bo b.nov","brief_def":"Ishbi-benob","full_def":""},"H3431":{"strong":"H3431","word":"יִשְׁבַּח","translit":"yish.bach","brief_def":"Ishbah","full_def":""},"H3432":{"strong":"H3432","word":"יָשֻׁבִי","translit":"ya.shu.vi","brief_def":"Jashubite","full_def":""},"H3433":{"strong":"H3433","word":"יָשֻׁ֫בִי לָ֑חֶם","translit":"ya.shu.vi le.chem","brief_def":"Lehem","full_def":""},"H3434":{"strong":"H3434","word":"יָשׇׁבְעָם","translit":"ya.shov.am","brief_def":"Jashobeam","full_def":""},"H3435":{"strong":"H3435","word":"יִשְׁבָּק","translit":"yish.baq","brief_def":"Ishbak","full_def":""},"H3436":{"strong":"H3436","word":"יׇשְׁבְּקָ֫שָׁה","translit":"yosh.be.qa.shah","brief_def":"Joshbekashah","full_def":""},"H3437":{"strong":"H3437","word":"יָשׁוּב","translit":"ya.shuv","brief_def":"Jashub","full_def":""},"H3438":{"strong":"H3438","word":"יִשְׁוָה","translit":"yish.vah","brief_def":"Ishvah","full_def":""},"H3439":{"strong":"H3439","word":"יְשׁוֹחָיָה","translit":"ye.sho.cha.yah","brief_def":"Jeshohaiah","full_def":""},"H3440":{"strong":"H3440","word":"יִשְׁוִי","translit":"yish.vi","brief_def":"Ishvi","full_def":""},"H3441":{"strong":"H3441","word":"יִשְׁוִי","translit":"yish.vi","brief_def":"Ishvite","full_def":""},"H3442":{"strong":"H3442","word":"יֵשׁוּעַ","translit":"ye.shu.a","brief_def":"Jeshua","full_def":""},"H3443":{"strong":"H3443","word":"יֵשׁוּעַ","translit":"ye.shu.a","brief_def":"Jeshua","full_def":""},"H3444":{"strong":"H3444","word":"יְשׁוּעָה","translit":"ye.shu.ah","brief_def":"salvation","full_def":""},"H3445":{"strong":"H3445","word":"יֶ֫שַׁח","translit":"ye.shach","brief_def":"emptiness","full_def":""},"H3446":{"strong":"H3446","word":"יִשְׂחָק","translit":"yis.chaq","brief_def":"Isaac","full_def":""},"H3447":{"strong":"H3447","word":"יָשַׁט","translit":"ya.shat","brief_def":"to extend","full_def":""},"H3448":{"strong":"H3448","word":"יִשַׁי","translit":"yi.shay","brief_def":"Jesse","full_def":""},"H3449":{"strong":"H3449","word":"יִשִּׁיָּהוּ","translit":"yish.shiy.yah","brief_def":"Isshijah","full_def":""},"H3450":{"strong":"H3450","word":"יְשִׁימִאֵל","translit":"ye.shi.ma.el","brief_def":"Jesimiel","full_def":""},"H3451":{"strong":"H3451","word":"יְשִׁימָה","translit":"ye.shi.mah","brief_def":"desolation","full_def":""},"H3452":{"strong":"H3452","word":"יְשִׁימוֹן","translit":"ye.shi.mon","brief_def":"wilderness","full_def":""},"H3453":{"strong":"H3453","word":"יָשִׁישׁ","translit":"ya.shish","brief_def":"aged","full_def":""},"H3454":{"strong":"H3454","word":"יְשִׁישַׁי","translit":"ye.shi.sah","brief_def":"Jeshishai","full_def":""},"H3455":{"strong":"H3455","word":"יָשַׂם","translit":"ya.sam","brief_def":"to put","full_def":""},"H3456":{"strong":"H3456","word":"יָשַׁם","translit":"ya.sham","brief_def":"be desolate","full_def":""},"H3457":{"strong":"H3457","word":"יִשְׁמָא","translit":"yish.ma","brief_def":"Ishma","full_def":""},"H3458":{"strong":"H3458","word":"יִשְׁמָעֵאל","translit":"yish.ma.el","brief_def":"Ishmael","full_def":""},"H3459":{"strong":"H3459","word":"יִשְׁמְעֵאלִי","translit":"yish.ma.e.li","brief_def":"Ishmaelite","full_def":""},"H3460":{"strong":"H3460","word":"יִשְׁמַעְיָ֫הוּ","translit":"yish.ma.yah","brief_def":"Ishmaiah","full_def":""},"H3461":{"strong":"H3461","word":"יִשְׁמְרַי","translit":"yish.me.ray","brief_def":"Ishmerai","full_def":""},"H3462":{"strong":"H3462","word":"יָשֵׁן","translit":"ya.shen","brief_def":"to sleep","full_def":""},"H3463":{"strong":"H3463","word":"יָשֵׁן","translit":"ya.shen","brief_def":"sleeping","full_def":""},"H3464":{"strong":"H3464","word":"יָשֵׁן","translit":"ya.shen","brief_def":"Jashen","full_def":""},"H3465":{"strong":"H3465","word":"יָשָׁן","translit":"ya.shan","brief_def":"old","full_def":""},"H3466":{"strong":"H3466","word":"יְשָׁנָה","translit":"ye.sha.nah","brief_def":"(Gate of) Yeshanah","full_def":""},"H3467":{"strong":"H3467","word":"יָשַׁע","translit":"ya.sah","brief_def":"to save","full_def":""},"H3468":{"strong":"H3468","word":"יֵ֫שַׁע","translit":"ye.sah","brief_def":"salvation","full_def":""},"H3469":{"strong":"H3469","word":"יִשְׁעִי","translit":"yish.i","brief_def":"Ishi","full_def":""},"H3470a":{"strong":"H3470a","word":"יְשַׁעְיָ֫הוּ","translit":"ye.sha.yah","brief_def":"Jeshaiah","full_def":""},"H3470b":{"strong":"H3470b","word":"יְשַׁעְיָה","translit":"ye.sha.yah","brief_def":"Jeshaiah","full_def":""},"H3471":{"strong":"H3471","word":"יָֽשְׁפֶה","translit":"ya.she.pheh","brief_def":"jasper","full_def":""},"H3472":{"strong":"H3472","word":"יִשְׁפָּה","translit":"yish.pah","brief_def":"Ishpah","full_def":""},"H3473":{"strong":"H3473","word":"יִשְׁפָּן","translit":"yish.pan","brief_def":"Ishpan","full_def":""},"H3474":{"strong":"H3474","word":"יָשַׁר","translit":"ya.shar","brief_def":"to smooth","full_def":""},"H3475":{"strong":"H3475","word":"יֶ֫שֶׁר","translit":"ye.sher","brief_def":"Jesher","full_def":""},"H3476":{"strong":"H3476","word":"יֹ֫שֶׁר","translit":"yo.sher","brief_def":"uprightness","full_def":""},"H3477":{"strong":"H3477","word":"יָשָׁר","translit":"ya.shar","brief_def":"upright","full_def":""},"H3478":{"strong":"H3478","word":"יִשְׂרָאֵל","translit":"yis.ra.el","brief_def":"Israel","full_def":""},"H3479":{"strong":"H3479","word":"יִשְׂרָאֵל","translit":"yis.ra.el","brief_def":"Israel","full_def":""},"H3480":{"strong":"H3480","word":"יְשַׂרְאֵ֫לָה","translit":"ye.sar.e.lah","brief_def":"Jesharelah","full_def":""},"H3481":{"strong":"H3481","word":"יִשְׂרְאֵלִי","translit":"yis.r.e.li","brief_def":"Israelite","full_def":""},"H3482":{"strong":"H3482","word":"יִשְׂרְאֵלִית","translit":"yis.r.e.lit","brief_def":"Israelitess","full_def":""},"H3483":{"strong":"H3483","word":"יְשָׁרָה","translit":"yish.rah","brief_def":"uprightness","full_def":""},"H3484":{"strong":"H3484","word":"יְשֻׁרוּן","translit":"ye.shu.run","brief_def":"Jeshurun","full_def":""},"H3485":{"strong":"H3485","word":"יִשָּׂשכָר","translit":"yis.sa.s.khar","brief_def":"Issachar","full_def":""},"H3486":{"strong":"H3486","word":"יָשֵׁשׁ","translit":"ya.shesh","brief_def":"decrepit","full_def":""},"H3487":{"strong":"H3487","word":"יָת","translit":"yat","brief_def":"whom","full_def":""},"H3488":{"strong":"H3488","word":"יְתִב","translit":"ye.tiv","brief_def":"to dwell","full_def":""},"H3489":{"strong":"H3489","word":"יָתֵד","translit":"ya.ted","brief_def":"peg","full_def":""},"H3490":{"strong":"H3490","word":"יָתוֹם","translit":"ya.tom","brief_def":"orphan","full_def":""},"H3491":{"strong":"H3491","word":"יְתוּר","translit":"ya.tur","brief_def":"remainder","full_def":""},"H3492":{"strong":"H3492","word":"יַתִּיר","translit":"yat.tir","brief_def":"Jattir","full_def":""},"H3493":{"strong":"H3493","word":"יַתִּיר","translit":"yat.tir","brief_def":"preeminent","full_def":""},"H3494":{"strong":"H3494","word":"יִתְלָה","translit":"yit.lah","brief_def":"Ithlah","full_def":""},"H3495":{"strong":"H3495","word":"יִתְמָה","translit":"yit.mah","brief_def":"Ithmah","full_def":""},"H3496":{"strong":"H3496","word":"יַתְנִיאֵל","translit":"yat.ni.el","brief_def":"Jathniel","full_def":""},"H3497":{"strong":"H3497","word":"יִתְנָ֑ן","translit":"yit.nan","brief_def":"Ithnan","full_def":""},"H3498":{"strong":"H3498","word":"יָתַר","translit":"ya.tar","brief_def":"to remain","full_def":""},"H3499a":{"strong":"H3499a","word":"יֶ֫תֶר","translit":"ye.ter","brief_def":"remainder","full_def":""},"H3499b":{"strong":"H3499b","word":"יֶ֫תֶר","translit":"ye.ter","brief_def":"cord","full_def":""}}